MANIFEST.in
setup.py
django_grappelli_navbar.egg-info/PKG-INFO
django_grappelli_navbar.egg-info/SOURCES.txt
django_grappelli_navbar.egg-info/dependency_links.txt
django_grappelli_navbar.egg-info/requires.txt
django_grappelli_navbar.egg-info/top_level.txt
grappelli_navbar/__init__.py
grappelli_navbar/navbar.py
grappelli_navbar/nodes.py
grappelli_navbar/test_cases.py
grappelli_navbar/test_navbar.py
grappelli_navbar/test_settings.py
grappelli_navbar/test_urls.py
grappelli_navbar/templates/admin/base.html
grappelli_navbar/templates/admin/base.html~
grappelli_navbar/templates/grappelli/navbar.html
grappelli_navbar/templates/grappelli/navbar.html~
grappelli_navbar/templatetags/__init__.py
grappelli_navbar/templatetags/grappelli_navbar.py