Metadata-Version: 1.1
Name: django-grappelli-navbar
Version: 0.2.0
Summary: Navigation bar on Django administration
Home-page: http://github.com/mauler/django-grappelli-navbar
Author: Paulo Roberto Macedo Chaves
Author-email: proberto.macedo@gmail.com
License: BSD
Platform: UNKNOWN
Classifier: Development Status :: 5 - Production/Stable
Classifier: Intended Audience :: Developers
Classifier: License :: OSI Approved :: Apache Software License
Classifier: Programming Language :: Python
Classifier: Operating System :: OS Independent
Classifier: Topic :: Software Development :: Libraries
Classifier: Topic :: Utilities
Classifier: Environment :: Web Environment
Classifier: Framework :: Django
